{
  "symbol": "BTBT",
  "date": "2025-05-13",
  "bars": [
    {
      "t": "2025-05-13 13:30:00+00:00",
      "open": 2.23,
      "high": 2.26,
      "low": 2.22,
      "close": 2.25,
      "volume": 653389
    },
    {
      "t": "2025-05-13 13:31:00+00:00",
      "open": 2.26,
      "high": 2.265,
      "low": 2.25,
      "close": 2.265,
      "volume": 92466
    },
    {
      "t": "2025-05-13 13:32:00+00:00",
      "open": 2.262,
      "high": 2.262,
      "low": 2.24,
      "close": 2.25,
      "volume": 124442
    },
    {
      "t": "2025-05-13 13:33:00+00:00",
      "open": 2.255,
      "high": 2.27,
      "low": 2.25,
      "close": 2.2502,
      "volume": 162422
    },
    {
      "t": "2025-05-13 13:34:00+00:00",
      "open": 2.25,
      "high": 2.25,
      "low": 2.2235,
      "close": 2.225,
      "volume": 70102
    },
    {
      "t": "2025-05-13 13:35:00+00:00",
      "open": 2.2202,
      "high": 2.2554,
      "low": 2.2202,
      "close": 2.25,
      "volume": 154887
    },
    {
      "t": "2025-05-13 13:36:00+00:00",
      "open": 2.25,
      "high": 2.255,
      "low": 2.24,
      "close": 2.24,
      "volume": 100230
    },
    {
      "t": "2025-05-13 13:37:00+00:00",
      "open": 2.2346,
      "high": 2.24,
      "low": 2.23,
      "close": 2.2395,
      "volume": 33493
    },
    {
      "t": "2025-05-13 13:38:00+00:00",
      "open": 2.23,
      "high": 2.23,
      "low": 2.2213,
      "close": 2.2254,
      "volume": 77397
    },
    {
      "t": "2025-05-13 13:39:00+00:00",
      "open": 2.225,
      "high": 2.23,
      "low": 2.22,
      "close": 2.2254,
      "volume": 17865
    },
    {
      "t": "2025-05-13 13:40:00+00:00",
      "open": 2.23,
      "high": 2.23,
      "low": 2.22,
      "close": 2.225,
      "volume": 35888
    },
    {
      "t": "2025-05-13 13:41:00+00:00",
      "open": 2.2207,
      "high": 2.23,
      "low": 2.2207,
      "close": 2.23,
      "volume": 15562
    },
    {
      "t": "2025-05-13 13:42:00+00:00",
      "open": 2.2299,
      "high": 2.23,
      "low": 2.22,
      "close": 2.23,
      "volume": 59518
    },
    {
      "t": "2025-05-13 13:43:00+00:00",
      "open": 2.2254,
      "high": 2.2254,
      "low": 2.2019,
      "close": 2.2098,
      "volume": 67106
    },
    {
      "t": "2025-05-13 13:44:00+00:00",
      "open": 2.205,
      "high": 2.21,
      "low": 2.2,
      "close": 2.2002,
      "volume": 55826
    },
    {
      "t": "2025-05-13 13:45:00+00:00",
      "open": 2.2047,
      "high": 2.21,
      "low": 2.19,
      "close": 2.1974,
      "volume": 68103
    },
    {
      "t": "2025-05-13 13:46:00+00:00",
      "open": 2.195,
      "high": 2.2,
      "low": 2.185,
      "close": 2.185,
      "volume": 66146
    },
    {
      "t": "2025-05-13 13:47:00+00:00",
      "open": 2.19,
      "high": 2.19,
      "low": 2.18,
      "close": 2.1804,
      "volume": 18735
    },
    {
      "t": "2025-05-13 13:48:00+00:00",
      "open": 2.185,
      "high": 2.185,
      "low": 2.17,
      "close": 2.175,
      "volume": 38517
    },
    {
      "t": "2025-05-13 13:49:00+00:00",
      "open": 2.18,
      "high": 2.1899,
      "low": 2.18,
      "close": 2.1834,
      "volume": 48421
    },
    {
      "t": "2025-05-13 13:50:00+00:00",
      "open": 2.185,
      "high": 2.1898,
      "low": 2.18,
      "close": 2.185,
      "volume": 38401
    },
    {
      "t": "2025-05-13 13:51:00+00:00",
      "open": 2.19,
      "high": 2.2,
      "low": 2.18,
      "close": 2.189,
      "volume": 166972
    },
    {
      "t": "2025-05-13 13:52:00+00:00",
      "open": 2.19,
      "high": 2.2,
      "low": 2.18,
      "close": 2.19,
      "volume": 142043
    },
    {
      "t": "2025-05-13 13:53:00+00:00",
      "open": 2.18,
      "high": 2.2,
      "low": 2.18,
      "close": 2.1954,
      "volume": 108328
    },
    {
      "t": "2025-05-13 13:54:00+00:00",
      "open": 2.1962,
      "high": 2.1998,
      "low": 2.19,
      "close": 2.195,
      "volume": 28887
    },
    {
      "t": "2025-05-13 13:55:00+00:00",
      "open": 2.2,
      "high": 2.2,
      "low": 2.1801,
      "close": 2.185,
      "volume": 41986
    },
    {
      "t": "2025-05-13 13:56:00+00:00",
      "open": 2.18,
      "high": 2.18,
      "low": 2.17,
      "close": 2.175,
      "volume": 68591
    },
    {
      "t": "2025-05-13 13:57:00+00:00",
      "open": 2.1799,
      "high": 2.18,
      "low": 2.17,
      "close": 2.1799,
      "volume": 87037
    },
    {
      "t": "2025-05-13 13:58:00+00:00",
      "open": 2.1799,
      "high": 2.1865,
      "low": 2.1798,
      "close": 2.181,
      "volume": 83713
    },
    {
      "t": "2025-05-13 13:59:00+00:00",
      "open": 2.1802,
      "high": 2.19,
      "low": 2.18,
      "close": 2.18,
      "volume": 30721
    },
    {
      "t": "2025-05-13 14:00:00+00:00",
      "open": 2.185,
      "high": 2.185,
      "low": 2.1799,
      "close": 2.1799,
      "volume": 44119
    },
    {
      "t": "2025-05-13 14:01:00+00:00",
      "open": 2.17,
      "high": 2.18,
      "low": 2.17,
      "close": 2.1798,
      "volume": 96417
    },
    {
      "t": "2025-05-13 14:02:00+00:00",
      "open": 2.1796,
      "high": 2.18,
      "low": 2.1707,
      "close": 2.1707,
      "volume": 13135
    },
    {
      "t": "2025-05-13 14:03:00+00:00",
      "open": 2.1701,
      "high": 2.1754,
      "low": 2.1608,
      "close": 2.1608,
      "volume": 92739
    },
    {
      "t": "2025-05-13 14:04:00+00:00",
      "open": 2.17,
      "high": 2.17,
      "low": 2.16,
      "close": 2.165,
      "volume": 16430
    },
    {
      "t": "2025-05-13 14:05:00+00:00",
      "open": 2.17,
      "high": 2.17,
      "low": 2.16,
      "close": 2.1607,
      "volume": 7174
    },
    {
      "t": "2025-05-13 14:06:00+00:00",
      "open": 2.165,
      "high": 2.17,
      "low": 2.16,
      "close": 2.165,
      "volume": 75196
    },
    {
      "t": "2025-05-13 14:07:00+00:00",
      "open": 2.1696,
      "high": 2.1754,
      "low": 2.16,
      "close": 2.1707,
      "volume": 98893
    },
    {
      "t": "2025-05-13 14:08:00+00:00",
      "open": 2.175,
      "high": 2.18,
      "low": 2.17,
      "close": 2.1789,
      "volume": 4167
    },
    {
      "t": "2025-05-13 14:09:00+00:00",
      "open": 2.17,
      "high": 2.17,
      "low": 2.16,
      "close": 2.1679,
      "volume": 50033
    },
    {
      "t": "2025-05-13 14:10:00+00:00",
      "open": 2.1604,
      "high": 2.1604,
      "low": 2.15,
      "close": 2.155,
      "volume": 59075
    },
    {
      "t": "2025-05-13 14:11:00+00:00",
      "open": 2.155,
      "high": 2.155,
      "low": 2.15,
      "close": 2.15,
      "volume": 27849
    },
    {
      "t": "2025-05-13 14:12:00+00:00",
      "open": 2.15,
      "high": 2.1556,
      "low": 2.15,
      "close": 2.155,
      "volume": 47055
    },
    {
      "t": "2025-05-13 14:13:00+00:00",
      "open": 2.155,
      "high": 2.155,
      "low": 2.14,
      "close": 2.15,
      "volume": 193101
    },
    {
      "t": "2025-05-13 14:14:00+00:00",
      "open": 2.1459,
      "high": 2.15,
      "low": 2.1442,
      "close": 2.145,
      "volume": 35136
    },
    {
      "t": "2025-05-13 14:15:00+00:00",
      "open": 2.1494,
      "high": 2.15,
      "low": 2.14,
      "close": 2.15,
      "volume": 18452
    },
    {
      "t": "2025-05-13 14:16:00+00:00",
      "open": 2.145,
      "high": 2.15,
      "low": 2.145,
      "close": 2.1493,
      "volume": 9595
    },
    {
      "t": "2025-05-13 14:17:00+00:00",
      "open": 2.145,
      "high": 2.1598,
      "low": 2.14,
      "close": 2.159,
      "volume": 87699
    },
    {
      "t": "2025-05-13 14:18:00+00:00",
      "open": 2.155,
      "high": 2.16,
      "low": 2.15,
      "close": 2.155,
      "volume": 41447
    },
    {
      "t": "2025-05-13 14:19:00+00:00",
      "open": 2.16,
      "high": 2.16,
      "low": 2.1501,
      "close": 2.1573,
      "volume": 34702
    },
    {
      "t": "2025-05-13 14:20:00+00:00",
      "open": 2.155,
      "high": 2.16,
      "low": 2.1534,
      "close": 2.1546,
      "volume": 14620
    },
    {
      "t": "2025-05-13 14:21:00+00:00",
      "open": 2.155,
      "high": 2.1581,
      "low": 2.155,
      "close": 2.155,
      "volume": 18487
    },
    {
      "t": "2025-05-13 14:22:00+00:00",
      "open": 2.1569,
      "high": 2.1599,
      "low": 2.14,
      "close": 2.145,
      "volume": 82956
    },
    {
      "t": "2025-05-13 14:23:00+00:00",
      "open": 2.145,
      "high": 2.15,
      "low": 2.14,
      "close": 2.1499,
      "volume": 27688
    },
    {
      "t": "2025-05-13 14:24:00+00:00",
      "open": 2.145,
      "high": 2.15,
      "low": 2.14,
      "close": 2.145,
      "volume": 39928
    },
    {
      "t": "2025-05-13 14:25:00+00:00",
      "open": 2.145,
      "high": 2.1499,
      "low": 2.14,
      "close": 2.1499,
      "volume": 16906
    },
    {
      "t": "2025-05-13 14:26:00+00:00",
      "open": 2.15,
      "high": 2.15,
      "low": 2.145,
      "close": 2.145,
      "volume": 8129
    },
    {
      "t": "2025-05-13 14:27:00+00:00",
      "open": 2.15,
      "high": 2.15,
      "low": 2.14,
      "close": 2.145,
      "volume": 106601
    },
    {
      "t": "2025-05-13 14:28:00+00:00",
      "open": 2.14,
      "high": 2.15,
      "low": 2.14,
      "close": 2.145,
      "volume": 77288
    },
    {
      "t": "2025-05-13 14:29:00+00:00",
      "open": 2.145,
      "high": 2.15,
      "low": 2.1401,
      "close": 2.15,
      "volume": 15321
    },
    {
      "t": "2025-05-13 14:30:00+00:00",
      "open": 2.145,
      "high": 2.15,
      "low": 2.13,
      "close": 2.14,
      "volume": 319457
    },
    {
      "t": "2025-05-13 14:31:00+00:00",
      "open": 2.1351,
      "high": 2.14,
      "low": 2.13,
      "close": 2.1323,
      "volume": 73494
    },
    {
      "t": "2025-05-13 14:32:00+00:00",
      "open": 2.135,
      "high": 2.15,
      "low": 2.1301,
      "close": 2.135,
      "volume": 138379
    },
    {
      "t": "2025-05-13 14:33:00+00:00",
      "open": 2.1399,
      "high": 2.14,
      "low": 2.135,
      "close": 2.135,
      "volume": 3578
    },
    {
      "t": "2025-05-13 14:34:00+00:00",
      "open": 2.1346,
      "high": 2.15,
      "low": 2.1346,
      "close": 2.145,
      "volume": 108121
    },
    {
      "t": "2025-05-13 14:35:00+00:00",
      "open": 2.1449,
      "high": 2.1599,
      "low": 2.1449,
      "close": 2.1599,
      "volume": 54277
    },
    {
      "t": "2025-05-13 14:36:00+00:00",
      "open": 2.155,
      "high": 2.1572,
      "low": 2.1517,
      "close": 2.155,
      "volume": 11380
    },
    {
      "t": "2025-05-13 14:37:00+00:00",
      "open": 2.1598,
      "high": 2.16,
      "low": 2.155,
      "close": 2.155,
      "volume": 7368
    },
    {
      "t": "2025-05-13 14:38:00+00:00",
      "open": 2.1599,
      "high": 2.16,
      "low": 2.15,
      "close": 2.155,
      "volume": 28427
    },
    {
      "t": "2025-05-13 14:39:00+00:00",
      "open": 2.155,
      "high": 2.17,
      "low": 2.155,
      "close": 2.1675,
      "volume": 140734
    },
    {
      "t": "2025-05-13 14:40:00+00:00",
      "open": 2.165,
      "high": 2.17,
      "low": 2.1646,
      "close": 2.17,
      "volume": 20667
    },
    {
      "t": "2025-05-13 14:41:00+00:00",
      "open": 2.17,
      "high": 2.17,
      "low": 2.165,
      "close": 2.165,
      "volume": 7726
    },
    {
      "t": "2025-05-13 14:42:00+00:00",
      "open": 2.1681,
      "high": 2.17,
      "low": 2.16,
      "close": 2.17,
      "volume": 34528
    },
    {
      "t": "2025-05-13 14:43:00+00:00",
      "open": 2.165,
      "high": 2.1664,
      "low": 2.165,
      "close": 2.165,
      "volume": 2333
    },
    {
      "t": "2025-05-13 14:44:00+00:00",
      "open": 2.16,
      "high": 2.17,
      "low": 2.16,
      "close": 2.165,
      "volume": 187261
    },
    {
      "t": "2025-05-13 14:45:00+00:00",
      "open": 2.165,
      "high": 2.17,
      "low": 2.165,
      "close": 2.165,
      "volume": 54877
    },
    {
      "t": "2025-05-13 14:46:00+00:00",
      "open": 2.1699,
      "high": 2.17,
      "low": 2.16,
      "close": 2.16,
      "volume": 97113
    },
    {
      "t": "2025-05-13 14:47:00+00:00",
      "open": 2.1601,
      "high": 2.17,
      "low": 2.15,
      "close": 2.15,
      "volume": 69723
    },
    {
      "t": "2025-05-13 14:48:00+00:00",
      "open": 2.16,
      "high": 2.16,
      "low": 2.155,
      "close": 2.155,
      "volume": 4417
    },
    {
      "t": "2025-05-13 14:49:00+00:00",
      "open": 2.155,
      "high": 2.155,
      "low": 2.15,
      "close": 2.155,
      "volume": 12069
    },
    {
      "t": "2025-05-13 14:50:00+00:00",
      "open": 2.155,
      "high": 2.16,
      "low": 2.1507,
      "close": 2.16,
      "volume": 54928
    },
    {
      "t": "2025-05-13 14:51:00+00:00",
      "open": 2.1546,
      "high": 2.17,
      "low": 2.1546,
      "close": 2.1654,
      "volume": 70626
    },
    {
      "t": "2025-05-13 14:52:00+00:00",
      "open": 2.165,
      "high": 2.1799,
      "low": 2.165,
      "close": 2.175,
      "volume": 112730
    },
    {
      "t": "2025-05-13 14:53:00+00:00",
      "open": 2.1782,
      "high": 2.1782,
      "low": 2.1714,
      "close": 2.175,
      "volume": 4518
    },
    {
      "t": "2025-05-13 14:54:00+00:00",
      "open": 2.175,
      "high": 2.18,
      "low": 2.1701,
      "close": 2.175,
      "volume": 20677
    },
    {
      "t": "2025-05-13 14:55:00+00:00",
      "open": 2.1735,
      "high": 2.175,
      "low": 2.1735,
      "close": 2.175,
      "volume": 5623
    },
    {
      "t": "2025-05-13 14:56:00+00:00",
      "open": 2.175,
      "high": 2.175,
      "low": 2.175,
      "close": 2.175,
      "volume": 3240
    },
    {
      "t": "2025-05-13 14:57:00+00:00",
      "open": 2.175,
      "high": 2.18,
      "low": 2.1701,
      "close": 2.175,
      "volume": 27259
    },
    {
      "t": "2025-05-13 14:58:00+00:00",
      "open": 2.175,
      "high": 2.18,
      "low": 2.175,
      "close": 2.18,
      "volume": 4602
    },
    {
      "t": "2025-05-13 14:59:00+00:00",
      "open": 2.18,
      "high": 2.18,
      "low": 2.1738,
      "close": 2.18,
      "volume": 4366
    },
    {
      "t": "2025-05-13 15:00:00+00:00",
      "open": 2.175,
      "high": 2.18,
      "low": 2.1747,
      "close": 2.175,
      "volume": 6583
    },
    {
      "t": "2025-05-13 15:01:00+00:00",
      "open": 2.175,
      "high": 2.18,
      "low": 2.175,
      "close": 2.177,
      "volume": 4582
    },
    {
      "t": "2025-05-13 15:02:00+00:00",
      "open": 2.175,
      "high": 2.175,
      "low": 2.17,
      "close": 2.1701,
      "volume": 4142
    },
    {
      "t": "2025-05-13 15:03:00+00:00",
      "open": 2.175,
      "high": 2.18,
      "low": 2.1701,
      "close": 2.1788,
      "volume": 25094
    },
    {
      "t": "2025-05-13 15:04:00+00:00",
      "open": 2.175,
      "high": 2.18,
      "low": 2.1732,
      "close": 2.175,
      "volume": 10828
    },
    {
      "t": "2025-05-13 15:05:00+00:00",
      "open": 2.175,
      "high": 2.185,
      "low": 2.1701,
      "close": 2.185,
      "volume": 51314
    },
    {
      "t": "2025-05-13 15:06:00+00:00",
      "open": 2.19,
      "high": 2.19,
      "low": 2.18,
      "close": 2.19,
      "volume": 21613
    },
    {
      "t": "2025-05-13 15:07:00+00:00",
      "open": 2.19,
      "high": 2.19,
      "low": 2.19,
      "close": 2.19,
      "volume": 2100
    },
    {
      "t": "2025-05-13 15:08:00+00:00",
      "open": 2.1845,
      "high": 2.1845,
      "low": 2.1845,
      "close": 2.1845,
      "volume": 146649
    },
    {
      "t": "2025-05-13 15:09:00+00:00",
      "open": 2.1897,
      "high": 2.1897,
      "low": 2.185,
      "close": 2.185,
      "volume": 4221
    },
    {
      "t": "2025-05-13 15:10:00+00:00",
      "open": 2.1808,
      "high": 2.19,
      "low": 2.18,
      "close": 2.1801,
      "volume": 118350
    },
    {
      "t": "2025-05-13 15:11:00+00:00",
      "open": 2.19,
      "high": 2.19,
      "low": 2.18,
      "close": 2.185,
      "volume": 10355
    },
    {
      "t": "2025-05-13 15:12:00+00:00",
      "open": 2.185,
      "high": 2.185,
      "low": 2.18,
      "close": 2.185,
      "volume": 7363
    },
    {
      "t": "2025-05-13 15:13:00+00:00",
      "open": 2.185,
      "high": 2.19,
      "low": 2.185,
      "close": 2.19,
      "volume": 14590
    },
    {
      "t": "2025-05-13 15:14:00+00:00",
      "open": 2.19,
      "high": 2.2,
      "low": 2.18,
      "close": 2.1831,
      "volume": 496761
    },
    {
      "t": "2025-05-13 15:15:00+00:00",
      "open": 2.1801,
      "high": 2.1899,
      "low": 2.18,
      "close": 2.1897,
      "volume": 43482
    },
    {
      "t": "2025-05-13 15:16:00+00:00",
      "open": 2.1842,
      "high": 2.1899,
      "low": 2.1808,
      "close": 2.1899,
      "volume": 2257
    },
    {
      "t": "2025-05-13 15:17:00+00:00",
      "open": 2.19,
      "high": 2.2,
      "low": 2.19,
      "close": 2.1993,
      "volume": 43142
    },
    {
      "t": "2025-05-13 15:18:00+00:00",
      "open": 2.19,
      "high": 2.195,
      "low": 2.19,
      "close": 2.195,
      "volume": 3200
    },
    {
      "t": "2025-05-13 15:19:00+00:00",
      "open": 2.195,
      "high": 2.1963,
      "low": 2.19,
      "close": 2.195,
      "volume": 45915
    },
    {
      "t": "2025-05-13 15:20:00+00:00",
      "open": 2.1901,
      "high": 2.1997,
      "low": 2.19,
      "close": 2.195,
      "volume": 56507
    },
    {
      "t": "2025-05-13 15:21:00+00:00",
      "open": 2.195,
      "high": 2.195,
      "low": 2.195,
      "close": 2.195,
      "volume": 2410
    },
    {
      "t": "2025-05-13 15:22:00+00:00",
      "open": 2.1918,
      "high": 2.1961,
      "low": 2.1907,
      "close": 2.195,
      "volume": 4699
    },
    {
      "t": "2025-05-13 15:23:00+00:00",
      "open": 2.195,
      "high": 2.1999,
      "low": 2.1901,
      "close": 2.195,
      "volume": 8837
    },
    {
      "t": "2025-05-13 15:24:00+00:00",
      "open": 2.1968,
      "high": 2.2,
      "low": 2.1923,
      "close": 2.195,
      "volume": 10905
    },
    {
      "t": "2025-05-13 15:25:00+00:00",
      "open": 2.195,
      "high": 2.1999,
      "low": 2.19,
      "close": 2.19,
      "volume": 41177
    },
    {
      "t": "2025-05-13 15:26:00+00:00",
      "open": 2.2,
      "high": 2.2,
      "low": 2.1908,
      "close": 2.195,
      "volume": 3716
    },
    {
      "t": "2025-05-13 15:27:00+00:00",
      "open": 2.195,
      "high": 2.2,
      "low": 2.19,
      "close": 2.195,
      "volume": 26844
    },
    {
      "t": "2025-05-13 15:28:00+00:00",
      "open": 2.195,
      "high": 2.2,
      "low": 2.195,
      "close": 2.195,
      "volume": 4619
    },
    {
      "t": "2025-05-13 15:29:00+00:00",
      "open": 2.2,
      "high": 2.2,
      "low": 2.195,
      "close": 2.195,
      "volume": 3622
    },
    {
      "t": "2025-05-13 15:30:00+00:00",
      "open": 2.195,
      "high": 2.2,
      "low": 2.19,
      "close": 2.195,
      "volume": 8551
    },
    {
      "t": "2025-05-13 15:31:00+00:00",
      "open": 2.19,
      "high": 2.2,
      "low": 2.19,
      "close": 2.2,
      "volume": 7855
    },
    {
      "t": "2025-05-13 15:32:00+00:00",
      "open": 2.195,
      "high": 2.1969,
      "low": 2.1928,
      "close": 2.195,
      "volume": 19636
    },
    {
      "t": "2025-05-13 15:33:00+00:00",
      "open": 2.195,
      "high": 2.1969,
      "low": 2.19,
      "close": 2.195,
      "volume": 3875
    },
    {
      "t": "2025-05-13 15:34:00+00:00",
      "open": 2.195,
      "high": 2.2,
      "low": 2.1929,
      "close": 2.195,
      "volume": 9784
    },
    {
      "t": "2025-05-13 15:35:00+00:00",
      "open": 2.19,
      "high": 2.195,
      "low": 2.185,
      "close": 2.185,
      "volume": 67560
    },
    {
      "t": "2025-05-13 15:36:00+00:00",
      "open": 2.185,
      "high": 2.185,
      "low": 2.18,
      "close": 2.185,
      "volume": 4986
    },
    {
      "t": "2025-05-13 15:37:00+00:00",
      "open": 2.1827,
      "high": 2.1858,
      "low": 2.18,
      "close": 2.1801,
      "volume": 116551
    },
    {
      "t": "2025-05-13 15:38:00+00:00",
      "open": 2.1854,
      "high": 2.1899,
      "low": 2.18,
      "close": 2.1818,
      "volume": 47719
    },
    {
      "t": "2025-05-13 15:39:00+00:00",
      "open": 2.185,
      "high": 2.185,
      "low": 2.1849,
      "close": 2.1849,
      "volume": 2148
    },
    {
      "t": "2025-05-13 15:40:00+00:00",
      "open": 2.18,
      "high": 2.185,
      "low": 2.18,
      "close": 2.185,
      "volume": 5832
    },
    {
      "t": "2025-05-13 15:41:00+00:00",
      "open": 2.18,
      "high": 2.1863,
      "low": 2.18,
      "close": 2.185,
      "volume": 5872
    },
    {
      "t": "2025-05-13 15:42:00+00:00",
      "open": 2.185,
      "high": 2.19,
      "low": 2.1825,
      "close": 2.1892,
      "volume": 4453
    },
    {
      "t": "2025-05-13 15:43:00+00:00",
      "open": 2.185,
      "high": 2.1865,
      "low": 2.1847,
      "close": 2.1865,
      "volume": 14944
    },
    {
      "t": "2025-05-13 15:44:00+00:00",
      "open": 2.19,
      "high": 2.19,
      "low": 2.185,
      "close": 2.1899,
      "volume": 99012
    },
    {
      "t": "2025-05-13 15:45:00+00:00",
      "open": 2.185,
      "high": 2.185,
      "low": 2.185,
      "close": 2.185,
      "volume": 2326
    },
    {
      "t": "2025-05-13 15:46:00+00:00",
      "open": 2.185,
      "high": 2.185,
      "low": 2.1818,
      "close": 2.1818,
      "volume": 12590
    },
    {
      "t": "2025-05-13 15:47:00+00:00",
      "open": 2.19,
      "high": 2.195,
      "low": 2.1801,
      "close": 2.195,
      "volume": 76260
    },
    {
      "t": "2025-05-13 15:48:00+00:00",
      "open": 2.1946,
      "high": 2.1999,
      "low": 2.1941,
      "close": 2.195,
      "volume": 31539
    },
    {
      "t": "2025-05-13 15:49:00+00:00",
      "open": 2.195,
      "high": 2.195,
      "low": 2.195,
      "close": 2.195,
      "volume": 4017
    },
    {
      "t": "2025-05-13 15:50:00+00:00",
      "open": 2.1944,
      "high": 2.2,
      "low": 2.1901,
      "close": 2.193,
      "volume": 18640
    },
    {
      "t": "2025-05-13 15:51:00+00:00",
      "open": 2.195,
      "high": 2.2,
      "low": 2.1901,
      "close": 2.1999,
      "volume": 18315
    },
    {
      "t": "2025-05-13 15:52:00+00:00",
      "open": 2.195,
      "high": 2.2,
      "low": 2.19,
      "close": 2.195,
      "volume": 1849
    },
    {
      "t": "2025-05-13 15:53:00+00:00",
      "open": 2.195,
      "high": 2.195,
      "low": 2.19,
      "close": 2.195,
      "volume": 2917
    },
    {
      "t": "2025-05-13 15:54:00+00:00",
      "open": 2.195,
      "high": 2.195,
      "low": 2.19,
      "close": 2.19,
      "volume": 8991
    },
    {
      "t": "2025-05-13 15:55:00+00:00",
      "open": 2.195,
      "high": 2.195,
      "low": 2.19,
      "close": 2.195,
      "volume": 5237
    },
    {
      "t": "2025-05-13 15:56:00+00:00",
      "open": 2.192,
      "high": 2.2,
      "low": 2.192,
      "close": 2.195,
      "volume": 10578
    },
    {
      "t": "2025-05-13 15:57:00+00:00",
      "open": 2.195,
      "high": 2.1999,
      "low": 2.19,
      "close": 2.195,
      "volume": 69902
    },
    {
      "t": "2025-05-13 15:58:00+00:00",
      "open": 2.195,
      "high": 2.1999,
      "low": 2.1922,
      "close": 2.1969,
      "volume": 15249
    },
    {
      "t": "2025-05-13 15:59:00+00:00",
      "open": 2.1998,
      "high": 2.1998,
      "low": 2.195,
      "close": 2.195,
      "volume": 3113
    },
    {
      "t": "2025-05-13 16:00:00+00:00",
      "open": 2.195,
      "high": 2.2066,
      "low": 2.195,
      "close": 2.205,
      "volume": 192748
    },
    {
      "t": "2025-05-13 16:01:00+00:00",
      "open": 2.2,
      "high": 2.21,
      "low": 2.1954,
      "close": 2.1994,
      "volume": 75785
    },
    {
      "t": "2025-05-13 16:02:00+00:00",
      "open": 2.195,
      "high": 2.2,
      "low": 2.19,
      "close": 2.2,
      "volume": 28704
    },
    {
      "t": "2025-05-13 16:03:00+00:00",
      "open": 2.1999,
      "high": 2.1999,
      "low": 2.1924,
      "close": 2.195,
      "volume": 3232
    },
    {
      "t": "2025-05-13 16:04:00+00:00",
      "open": 2.195,
      "high": 2.195,
      "low": 2.195,
      "close": 2.195,
      "volume": 1696
    },
    {
      "t": "2025-05-13 16:05:00+00:00",
      "open": 2.195,
      "high": 2.2,
      "low": 2.19,
      "close": 2.19,
      "volume": 2344
    },
    {
      "t": "2025-05-13 16:06:00+00:00",
      "open": 2.195,
      "high": 2.2,
      "low": 2.195,
      "close": 2.195,
      "volume": 2378
    },
    {
      "t": "2025-05-13 16:07:00+00:00",
      "open": 2.195,
      "high": 2.195,
      "low": 2.195,
      "close": 2.195,
      "volume": 5081
    },
    {
      "t": "2025-05-13 16:08:00+00:00",
      "open": 2.195,
      "high": 2.2,
      "low": 2.195,
      "close": 2.1999,
      "volume": 3933
    },
    {
      "t": "2025-05-13 16:09:00+00:00",
      "open": 2.195,
      "high": 2.2,
      "low": 2.19,
      "close": 2.195,
      "volume": 9867
    },
    {
      "t": "2025-05-13 16:10:00+00:00",
      "open": 2.1902,
      "high": 2.2,
      "low": 2.1902,
      "close": 2.2,
      "volume": 28116
    },
    {
      "t": "2025-05-13 16:11:00+00:00",
      "open": 2.19,
      "high": 2.195,
      "low": 2.19,
      "close": 2.195,
      "volume": 5810
    },
    {
      "t": "2025-05-13 16:12:00+00:00",
      "open": 2.19,
      "high": 2.2,
      "low": 2.19,
      "close": 2.195,
      "volume": 108520
    },
    {
      "t": "2025-05-13 16:13:00+00:00",
      "open": 2.195,
      "high": 2.21,
      "low": 2.195,
      "close": 2.21,
      "volume": 181554
    },
    {
      "t": "2025-05-13 16:14:00+00:00",
      "open": 2.205,
      "high": 2.2199,
      "low": 2.2046,
      "close": 2.216,
      "volume": 156413
    },
    {
      "t": "2025-05-13 16:15:00+00:00",
      "open": 2.22,
      "high": 2.22,
      "low": 2.21,
      "close": 2.2159,
      "volume": 68489
    },
    {
      "t": "2025-05-13 16:16:00+00:00",
      "open": 2.215,
      "high": 2.22,
      "low": 2.21,
      "close": 2.215,
      "volume": 20769
    },
    {
      "t": "2025-05-13 16:17:00+00:00",
      "open": 2.215,
      "high": 2.2192,
      "low": 2.2101,
      "close": 2.2192,
      "volume": 15233
    },
    {
      "t": "2025-05-13 16:18:00+00:00",
      "open": 2.2172,
      "high": 2.22,
      "low": 2.2101,
      "close": 2.215,
      "volume": 42070
    },
    {
      "t": "2025-05-13 16:19:00+00:00",
      "open": 2.215,
      "high": 2.215,
      "low": 2.215,
      "close": 2.215,
      "volume": 4587
    },
    {
      "t": "2025-05-13 16:20:00+00:00",
      "open": 2.213,
      "high": 2.213,
      "low": 2.2001,
      "close": 2.21,
      "volume": 147598
    },
    {
      "t": "2025-05-13 16:21:00+00:00",
      "open": 2.2053,
      "high": 2.2053,
      "low": 2.205,
      "close": 2.205,
      "volume": 5199
    },
    {
      "t": "2025-05-13 16:22:00+00:00",
      "open": 2.2087,
      "high": 2.21,
      "low": 2.205,
      "close": 2.205,
      "volume": 13324
    },
    {
      "t": "2025-05-13 16:23:00+00:00",
      "open": 2.2,
      "high": 2.2054,
      "low": 2.2,
      "close": 2.205,
      "volume": 38607
    },
    {
      "t": "2025-05-13 16:24:00+00:00",
      "open": 2.2099,
      "high": 2.2099,
      "low": 2.205,
      "close": 2.205,
      "volume": 16332
    },
    {
      "t": "2025-05-13 16:25:00+00:00",
      "open": 2.207,
      "high": 2.21,
      "low": 2.2,
      "close": 2.21,
      "volume": 39686
    },
    {
      "t": "2025-05-13 16:26:00+00:00",
      "open": 2.2046,
      "high": 2.21,
      "low": 2.2046,
      "close": 2.205,
      "volume": 2288
    },
    {
      "t": "2025-05-13 16:27:00+00:00",
      "open": 2.2097,
      "high": 2.22,
      "low": 2.2,
      "close": 2.2,
      "volume": 332490
    },
    {
      "t": "2025-05-13 16:28:00+00:00",
      "open": 2.2068,
      "high": 2.21,
      "low": 2.2,
      "close": 2.205,
      "volume": 42434
    },
    {
      "t": "2025-05-13 16:29:00+00:00",
      "open": 2.2046,
      "high": 2.205,
      "low": 2.2,
      "close": 2.205,
      "volume": 3852
    },
    {
      "t": "2025-05-13 16:30:00+00:00",
      "open": 2.2,
      "high": 2.205,
      "low": 2.1942,
      "close": 2.1959,
      "volume": 89509
    },
    {
      "t": "2025-05-13 16:31:00+00:00",
      "open": 2.195,
      "high": 2.205,
      "low": 2.19,
      "close": 2.205,
      "volume": 81756
    },
    {
      "t": "2025-05-13 16:32:00+00:00",
      "open": 2.205,
      "high": 2.205,
      "low": 2.205,
      "close": 2.205,
      "volume": 23125
    },
    {
      "t": "2025-05-13 16:33:00+00:00",
      "open": 2.2051,
      "high": 2.21,
      "low": 2.205,
      "close": 2.21,
      "volume": 4864
    },
    {
      "t": "2025-05-13 16:34:00+00:00",
      "open": 2.205,
      "high": 2.205,
      "low": 2.205,
      "close": 2.205,
      "volume": 18594
    },
    {
      "t": "2025-05-13 16:35:00+00:00",
      "open": 2.2,
      "high": 2.21,
      "low": 2.2,
      "close": 2.2,
      "volume": 65851
    },
    {
      "t": "2025-05-13 16:36:00+00:00",
      "open": 2.2099,
      "high": 2.22,
      "low": 2.205,
      "close": 2.21,
      "volume": 229813
    },
    {
      "t": "2025-05-13 16:37:00+00:00",
      "open": 2.2101,
      "high": 2.2101,
      "low": 2.2,
      "close": 2.2,
      "volume": 77069
    },
    {
      "t": "2025-05-13 16:38:00+00:00",
      "open": 2.2092,
      "high": 2.2097,
      "low": 2.2,
      "close": 2.2007,
      "volume": 2404
    },
    {
      "t": "2025-05-13 16:39:00+00:00",
      "open": 2.2,
      "high": 2.205,
      "low": 2.2,
      "close": 2.205,
      "volume": 1224
    },
    {
      "t": "2025-05-13 16:40:00+00:00",
      "open": 2.205,
      "high": 2.2092,
      "low": 2.2,
      "close": 2.205,
      "volume": 8372
    },
    {
      "t": "2025-05-13 16:41:00+00:00",
      "open": 2.206,
      "high": 2.206,
      "low": 2.2,
      "close": 2.205,
      "volume": 8534
    },
    {
      "t": "2025-05-13 16:42:00+00:00",
      "open": 2.2,
      "high": 2.21,
      "low": 2.2,
      "close": 2.2,
      "volume": 15073
    },
    {
      "t": "2025-05-13 16:43:00+00:00",
      "open": 2.205,
      "high": 2.21,
      "low": 2.2,
      "close": 2.2,
      "volume": 16297
    },
    {
      "t": "2025-05-13 16:44:00+00:00",
      "open": 2.205,
      "high": 2.205,
      "low": 2.1945,
      "close": 2.195,
      "volume": 20062
    },
    {
      "t": "2025-05-13 16:45:00+00:00",
      "open": 2.195,
      "high": 2.2,
      "low": 2.195,
      "close": 2.1964,
      "volume": 12218
    },
    {
      "t": "2025-05-13 16:46:00+00:00",
      "open": 2.1966,
      "high": 2.1966,
      "low": 2.195,
      "close": 2.1951,
      "volume": 2652
    },
    {
      "t": "2025-05-13 16:47:00+00:00",
      "open": 2.1999,
      "high": 2.2,
      "low": 2.1964,
      "close": 2.1977,
      "volume": 31276
    },
    {
      "t": "2025-05-13 16:48:00+00:00",
      "open": 2.2,
      "high": 2.2,
      "low": 2.1946,
      "close": 2.2,
      "volume": 16861
    },
    {
      "t": "2025-05-13 16:49:00+00:00",
      "open": 2.1942,
      "high": 2.2,
      "low": 2.1942,
      "close": 2.2,
      "volume": 758
    },
    {
      "t": "2025-05-13 16:50:00+00:00",
      "open": 2.2,
      "high": 2.2,
      "low": 2.1901,
      "close": 2.195,
      "volume": 14481
    },
    {
      "t": "2025-05-13 16:51:00+00:00",
      "open": 2.195,
      "high": 2.195,
      "low": 2.195,
      "close": 2.195,
      "volume": 871
    },
    {
      "t": "2025-05-13 16:52:00+00:00",
      "open": 2.195,
      "high": 2.2,
      "low": 2.195,
      "close": 2.2,
      "volume": 583
    },
    {
      "t": "2025-05-13 16:53:00+00:00",
      "open": 2.1901,
      "high": 2.2,
      "low": 2.1901,
      "close": 2.195,
      "volume": 31739
    },
    {
      "t": "2025-05-13 16:54:00+00:00",
      "open": 2.195,
      "high": 2.2,
      "low": 2.195,
      "close": 2.195,
      "volume": 9240
    },
    {
      "t": "2025-05-13 16:55:00+00:00",
      "open": 2.195,
      "high": 2.195,
      "low": 2.19,
      "close": 2.195,
      "volume": 2386
    },
    {
      "t": "2025-05-13 16:56:00+00:00",
      "open": 2.195,
      "high": 2.1973,
      "low": 2.18,
      "close": 2.18,
      "volume": 77935
    },
    {
      "t": "2025-05-13 16:57:00+00:00",
      "open": 2.185,
      "high": 2.185,
      "low": 2.185,
      "close": 2.185,
      "volume": 670
    },
    {
      "t": "2025-05-13 16:58:00+00:00",
      "open": 2.185,
      "high": 2.185,
      "low": 2.185,
      "close": 2.185,
      "volume": 1920
    },
    {
      "t": "2025-05-13 16:59:00+00:00",
      "open": 2.185,
      "high": 2.185,
      "low": 2.18,
      "close": 2.18,
      "volume": 3330
    },
    {
      "t": "2025-05-13 17:00:00+00:00",
      "open": 2.185,
      "high": 2.19,
      "low": 2.18,
      "close": 2.1834,
      "volume": 2647
    },
    {
      "t": "2025-05-13 17:01:00+00:00",
      "open": 2.185,
      "high": 2.1899,
      "low": 2.18,
      "close": 2.18,
      "volume": 3714
    },
    {
      "t": "2025-05-13 17:02:00+00:00",
      "open": 2.19,
      "high": 2.19,
      "low": 2.185,
      "close": 2.185,
      "volume": 689
    },
    {
      "t": "2025-05-13 17:03:00+00:00",
      "open": 2.1816,
      "high": 2.19,
      "low": 2.18,
      "close": 2.185,
      "volume": 16104
    },
    {
      "t": "2025-05-13 17:04:00+00:00",
      "open": 2.19,
      "high": 2.19,
      "low": 2.185,
      "close": 2.19,
      "volume": 10836
    },
    {
      "t": "2025-05-13 17:05:00+00:00",
      "open": 2.19,
      "high": 2.19,
      "low": 2.18,
      "close": 2.18,
      "volume": 8371
    },
    {
      "t": "2025-05-13 17:06:00+00:00",
      "open": 2.18,
      "high": 2.19,
      "low": 2.18,
      "close": 2.185,
      "volume": 5975
    },
    {
      "t": "2025-05-13 17:07:00+00:00",
      "open": 2.185,
      "high": 2.1899,
      "low": 2.1846,
      "close": 2.1846,
      "volume": 39240
    },
    {
      "t": "2025-05-13 17:08:00+00:00",
      "open": 2.185,
      "high": 2.19,
      "low": 2.1801,
      "close": 2.19,
      "volume": 41822
    },
    {
      "t": "2025-05-13 17:09:00+00:00",
      "open": 2.185,
      "high": 2.19,
      "low": 2.185,
      "close": 2.185,
      "volume": 14581
    },
    {
      "t": "2025-05-13 17:10:00+00:00",
      "open": 2.185,
      "high": 2.185,
      "low": 2.185,
      "close": 2.185,
      "volume": 880
    },
    {
      "t": "2025-05-13 17:11:00+00:00",
      "open": 2.18,
      "high": 2.19,
      "low": 2.18,
      "close": 2.185,
      "volume": 12066
    },
    {
      "t": "2025-05-13 17:12:00+00:00",
      "open": 2.185,
      "high": 2.1999,
      "low": 2.185,
      "close": 2.1936,
      "volume": 71477
    },
    {
      "t": "2025-05-13 17:13:00+00:00",
      "open": 2.195,
      "high": 2.195,
      "low": 2.195,
      "close": 2.195,
      "volume": 7516
    },
    {
      "t": "2025-05-13 17:14:00+00:00",
      "open": 2.195,
      "high": 2.2,
      "low": 2.1944,
      "close": 2.1944,
      "volume": 2082
    },
    {
      "t": "2025-05-13 17:15:00+00:00",
      "open": 2.195,
      "high": 2.21,
      "low": 2.195,
      "close": 2.205,
      "volume": 58418
    },
    {
      "t": "2025-05-13 17:16:00+00:00",
      "open": 2.2066,
      "high": 2.21,
      "low": 2.205,
      "close": 2.21,
      "volume": 816
    },
    {
      "t": "2025-05-13 17:17:00+00:00",
      "open": 2.205,
      "high": 2.21,
      "low": 2.2008,
      "close": 2.205,
      "volume": 23814
    },
    {
      "t": "2025-05-13 17:18:00+00:00",
      "open": 2.205,
      "high": 2.21,
      "low": 2.205,
      "close": 2.205,
      "volume": 1031
    },
    {
      "t": "2025-05-13 17:19:00+00:00",
      "open": 2.21,
      "high": 2.21,
      "low": 2.205,
      "close": 2.2053,
      "volume": 28195
    },
    {
      "t": "2025-05-13 17:20:00+00:00",
      "open": 2.21,
      "high": 2.21,
      "low": 2.205,
      "close": 2.21,
      "volume": 11638
    },
    {
      "t": "2025-05-13 17:21:00+00:00",
      "open": 2.21,
      "high": 2.21,
      "low": 2.205,
      "close": 2.205,
      "volume": 4267
    },
    {
      "t": "2025-05-13 17:22:00+00:00",
      "open": 2.205,
      "high": 2.22,
      "low": 2.2,
      "close": 2.21,
      "volume": 308739
    },
    {
      "t": "2025-05-13 17:23:00+00:00",
      "open": 2.21,
      "high": 2.2199,
      "low": 2.21,
      "close": 2.215,
      "volume": 4473
    },
    {
      "t": "2025-05-13 17:24:00+00:00",
      "open": 2.2199,
      "high": 2.22,
      "low": 2.215,
      "close": 2.22,
      "volume": 656
    },
    {
      "t": "2025-05-13 17:25:00+00:00",
      "open": 2.215,
      "high": 2.215,
      "low": 2.215,
      "close": 2.215,
      "volume": 1472
    },
    {
      "t": "2025-05-13 17:26:00+00:00",
      "open": 2.2144,
      "high": 2.22,
      "low": 2.2144,
      "close": 2.2199,
      "volume": 8422
    },
    {
      "t": "2025-05-13 17:27:00+00:00",
      "open": 2.21,
      "high": 2.215,
      "low": 2.205,
      "close": 2.205,
      "volume": 118424
    },
    {
      "t": "2025-05-13 17:28:00+00:00",
      "open": 2.205,
      "high": 2.2066,
      "low": 2.2,
      "close": 2.205,
      "volume": 5565
    },
    {
      "t": "2025-05-13 17:29:00+00:00",
      "open": 2.205,
      "high": 2.205,
      "low": 2.205,
      "close": 2.205,
      "volume": 1522
    },
    {
      "t": "2025-05-13 17:30:00+00:00",
      "open": 2.205,
      "high": 2.2056,
      "low": 2.205,
      "close": 2.205,
      "volume": 3052
    },
    {
      "t": "2025-05-13 17:31:00+00:00",
      "open": 2.2,
      "high": 2.205,
      "low": 2.2,
      "close": 2.205,
      "volume": 1058
    },
    {
      "t": "2025-05-13 17:32:00+00:00",
      "open": 2.2001,
      "high": 2.205,
      "low": 2.2001,
      "close": 2.205,
      "volume": 7037
    },
    {
      "t": "2025-05-13 17:33:00+00:00",
      "open": 2.205,
      "high": 2.21,
      "low": 2.2,
      "close": 2.205,
      "volume": 3840
    },
    {
      "t": "2025-05-13 17:34:00+00:00",
      "open": 2.205,
      "high": 2.205,
      "low": 2.2001,
      "close": 2.205,
      "volume": 5889
    },
    {
      "t": "2025-05-13 17:35:00+00:00",
      "open": 2.205,
      "high": 2.205,
      "low": 2.2,
      "close": 2.205,
      "volume": 920
    },
    {
      "t": "2025-05-13 17:36:00+00:00",
      "open": 2.2,
      "high": 2.205,
      "low": 2.2,
      "close": 2.205,
      "volume": 2488
    },
    {
      "t": "2025-05-13 17:37:00+00:00",
      "open": 2.205,
      "high": 2.2079,
      "low": 2.1901,
      "close": 2.1957,
      "volume": 99730
    },
    {
      "t": "2025-05-13 17:38:00+00:00",
      "open": 2.195,
      "high": 2.1967,
      "low": 2.19,
      "close": 2.195,
      "volume": 8137
    },
    {
      "t": "2025-05-13 17:39:00+00:00",
      "open": 2.195,
      "high": 2.195,
      "low": 2.19,
      "close": 2.19,
      "volume": 1618
    },
    {
      "t": "2025-05-13 17:40:00+00:00",
      "open": 2.19,
      "high": 2.21,
      "low": 2.19,
      "close": 2.205,
      "volume": 211015
    },
    {
      "t": "2025-05-13 17:41:00+00:00",
      "open": 2.2,
      "high": 2.21,
      "low": 2.2,
      "close": 2.21,
      "volume": 21828
    },
    {
      "t": "2025-05-13 17:42:00+00:00",
      "open": 2.205,
      "high": 2.205,
      "low": 2.205,
      "close": 2.205,
      "volume": 1097
    },
    {
      "t": "2025-05-13 17:43:00+00:00",
      "open": 2.205,
      "high": 2.205,
      "low": 2.205,
      "close": 2.205,
      "volume": 1397
    },
    {
      "t": "2025-05-13 17:44:00+00:00",
      "open": 2.205,
      "high": 2.2065,
      "low": 2.2001,
      "close": 2.205,
      "volume": 3931
    },
    {
      "t": "2025-05-13 17:45:00+00:00",
      "open": 2.205,
      "high": 2.205,
      "low": 2.2048,
      "close": 2.205,
      "volume": 2164
    },
    {
      "t": "2025-05-13 17:46:00+00:00",
      "open": 2.205,
      "high": 2.21,
      "low": 2.2,
      "close": 2.205,
      "volume": 4269
    },
    {
      "t": "2025-05-13 17:47:00+00:00",
      "open": 2.205,
      "high": 2.21,
      "low": 2.2,
      "close": 2.205,
      "volume": 31342
    },
    {
      "t": "2025-05-13 17:48:00+00:00",
      "open": 2.205,
      "high": 2.21,
      "low": 2.205,
      "close": 2.21,
      "volume": 23331
    },
    {
      "t": "2025-05-13 17:49:00+00:00",
      "open": 2.21,
      "high": 2.22,
      "low": 2.2,
      "close": 2.215,
      "volume": 59207
    },
    {
      "t": "2025-05-13 17:50:00+00:00",
      "open": 2.215,
      "high": 2.22,
      "low": 2.21,
      "close": 2.22,
      "volume": 9838
    },
    {
      "t": "2025-05-13 17:51:00+00:00",
      "open": 2.215,
      "high": 2.2166,
      "low": 2.214,
      "close": 2.215,
      "volume": 3188
    },
    {
      "t": "2025-05-13 17:52:00+00:00",
      "open": 2.215,
      "high": 2.215,
      "low": 2.2101,
      "close": 2.2139,
      "volume": 12752
    },
    {
      "t": "2025-05-13 17:53:00+00:00",
      "open": 2.2101,
      "high": 2.215,
      "low": 2.21,
      "close": 2.215,
      "volume": 22785
    },
    {
      "t": "2025-05-13 17:54:00+00:00",
      "open": 2.215,
      "high": 2.215,
      "low": 2.21,
      "close": 2.21,
      "volume": 4173
    },
    {
      "t": "2025-05-13 17:55:00+00:00",
      "open": 2.215,
      "high": 2.215,
      "low": 2.215,
      "close": 2.215,
      "volume": 1971
    },
    {
      "t": "2025-05-13 17:56:00+00:00",
      "open": 2.2166,
      "high": 2.2166,
      "low": 2.205,
      "close": 2.2086,
      "volume": 72229
    },
    {
      "t": "2025-05-13 17:57:00+00:00",
      "open": 2.2057,
      "high": 2.21,
      "low": 2.205,
      "close": 2.205,
      "volume": 5209
    },
    {
      "t": "2025-05-13 17:58:00+00:00",
      "open": 2.21,
      "high": 2.21,
      "low": 2.2,
      "close": 2.205,
      "volume": 4194
    },
    {
      "t": "2025-05-13 17:59:00+00:00",
      "open": 2.205,
      "high": 2.21,
      "low": 2.2043,
      "close": 2.205,
      "volume": 15140
    },
    {
      "t": "2025-05-13 18:00:00+00:00",
      "open": 2.21,
      "high": 2.21,
      "low": 2.2042,
      "close": 2.205,
      "volume": 16386
    },
    {
      "t": "2025-05-13 18:01:00+00:00",
      "open": 2.205,
      "high": 2.205,
      "low": 2.205,
      "close": 2.205,
      "volume": 6271
    },
    {
      "t": "2025-05-13 18:02:00+00:00",
      "open": 2.205,
      "high": 2.21,
      "low": 2.205,
      "close": 2.21,
      "volume": 5554
    },
    {
      "t": "2025-05-13 18:03:00+00:00",
      "open": 2.205,
      "high": 2.22,
      "low": 2.205,
      "close": 2.215,
      "volume": 203579
    },
    {
      "t": "2025-05-13 18:04:00+00:00",
      "open": 2.215,
      "high": 2.22,
      "low": 2.215,
      "close": 2.22,
      "volume": 5167
    },
    {
      "t": "2025-05-13 18:05:00+00:00",
      "open": 2.22,
      "high": 2.23,
      "low": 2.2137,
      "close": 2.23,
      "volume": 401410
    },
    {
      "t": "2025-05-13 18:06:00+00:00",
      "open": 2.22,
      "high": 2.23,
      "low": 2.22,
      "close": 2.22,
      "volume": 314572
    },
    {
      "t": "2025-05-13 18:07:00+00:00",
      "open": 2.2264,
      "high": 2.2264,
      "low": 2.22,
      "close": 2.22,
      "volume": 1365
    },
    {
      "t": "2025-05-13 18:08:00+00:00",
      "open": 2.225,
      "high": 2.225,
      "low": 2.2201,
      "close": 2.225,
      "volume": 3155
    },
    {
      "t": "2025-05-13 18:09:00+00:00",
      "open": 2.225,
      "high": 2.225,
      "low": 2.225,
      "close": 2.225,
      "volume": 651
    },
    {
      "t": "2025-05-13 18:10:00+00:00",
      "open": 2.225,
      "high": 2.23,
      "low": 2.225,
      "close": 2.225,
      "volume": 2680
    },
    {
      "t": "2025-05-13 18:11:00+00:00",
      "open": 2.225,
      "high": 2.23,
      "low": 2.2202,
      "close": 2.23,
      "volume": 28253
    },
    {
      "t": "2025-05-13 18:12:00+00:00",
      "open": 2.225,
      "high": 2.24,
      "low": 2.225,
      "close": 2.24,
      "volume": 245995
    },
    {
      "t": "2025-05-13 18:13:00+00:00",
      "open": 2.24,
      "high": 2.24,
      "low": 2.2301,
      "close": 2.235,
      "volume": 1663
    },
    {
      "t": "2025-05-13 18:14:00+00:00",
      "open": 2.235,
      "high": 2.24,
      "low": 2.235,
      "close": 2.235,
      "volume": 1897
    },
    {
      "t": "2025-05-13 18:15:00+00:00",
      "open": 2.235,
      "high": 2.235,
      "low": 2.23,
      "close": 2.235,
      "volume": 17191
    },
    {
      "t": "2025-05-13 18:16:00+00:00",
      "open": 2.235,
      "high": 2.2371,
      "low": 2.2308,
      "close": 2.2308,
      "volume": 7019
    },
    {
      "t": "2025-05-13 18:17:00+00:00",
      "open": 2.2346,
      "high": 2.24,
      "low": 2.23,
      "close": 2.23,
      "volume": 7790
    },
    {
      "t": "2025-05-13 18:18:00+00:00",
      "open": 2.235,
      "high": 2.24,
      "low": 2.23,
      "close": 2.235,
      "volume": 58757
    },
    {
      "t": "2025-05-13 18:19:00+00:00",
      "open": 2.23,
      "high": 2.24,
      "low": 2.23,
      "close": 2.235,
      "volume": 12829
    },
    {
      "t": "2025-05-13 18:20:00+00:00",
      "open": 2.235,
      "high": 2.24,
      "low": 2.23,
      "close": 2.235,
      "volume": 37889
    },
    {
      "t": "2025-05-13 18:21:00+00:00",
      "open": 2.235,
      "high": 2.24,
      "low": 2.23,
      "close": 2.2399,
      "volume": 21983
    },
    {
      "t": "2025-05-13 18:22:00+00:00",
      "open": 2.235,
      "high": 2.235,
      "low": 2.2306,
      "close": 2.235,
      "volume": 10574
    },
    {
      "t": "2025-05-13 18:23:00+00:00",
      "open": 2.2366,
      "high": 2.24,
      "low": 2.2346,
      "close": 2.2349,
      "volume": 7392
    },
    {
      "t": "2025-05-13 18:24:00+00:00",
      "open": 2.2347,
      "high": 2.24,
      "low": 2.2347,
      "close": 2.235,
      "volume": 2212
    },
    {
      "t": "2025-05-13 18:25:00+00:00",
      "open": 2.2351,
      "high": 2.24,
      "low": 2.2301,
      "close": 2.235,
      "volume": 53443
    },
    {
      "t": "2025-05-13 18:26:00+00:00",
      "open": 2.235,
      "high": 2.24,
      "low": 2.23,
      "close": 2.24,
      "volume": 7928
    },
    {
      "t": "2025-05-13 18:27:00+00:00",
      "open": 2.24,
      "high": 2.24,
      "low": 2.23,
      "close": 2.235,
      "volume": 6809
    },
    {
      "t": "2025-05-13 18:28:00+00:00",
      "open": 2.235,
      "high": 2.25,
      "low": 2.235,
      "close": 2.24,
      "volume": 442632
    },
    {
      "t": "2025-05-13 18:29:00+00:00",
      "open": 2.25,
      "high": 2.25,
      "low": 2.24,
      "close": 2.24,
      "volume": 7069
    },
    {
      "t": "2025-05-13 18:30:00+00:00",
      "open": 2.245,
      "high": 2.245,
      "low": 2.24,
      "close": 2.24,
      "volume": 1429
    },
    {
      "t": "2025-05-13 18:31:00+00:00",
      "open": 2.245,
      "high": 2.245,
      "low": 2.235,
      "close": 2.235,
      "volume": 88688
    },
    {
      "t": "2025-05-13 18:32:00+00:00",
      "open": 2.23,
      "high": 2.235,
      "low": 2.23,
      "close": 2.235,
      "volume": 2719
    },
    {
      "t": "2025-05-13 18:33:00+00:00",
      "open": 2.235,
      "high": 2.235,
      "low": 2.23,
      "close": 2.235,
      "volume": 6700
    },
    {
      "t": "2025-05-13 18:34:00+00:00",
      "open": 2.235,
      "high": 2.2359,
      "low": 2.2347,
      "close": 2.235,
      "volume": 3466
    },
    {
      "t": "2025-05-13 18:35:00+00:00",
      "open": 2.235,
      "high": 2.235,
      "low": 2.235,
      "close": 2.235,
      "volume": 1538
    },
    {
      "t": "2025-05-13 18:36:00+00:00",
      "open": 2.235,
      "high": 2.24,
      "low": 2.23,
      "close": 2.235,
      "volume": 8534
    },
    {
      "t": "2025-05-13 18:37:00+00:00",
      "open": 2.235,
      "high": 2.235,
      "low": 2.235,
      "close": 2.235,
      "volume": 613
    },
    {
      "t": "2025-05-13 18:38:00+00:00",
      "open": 2.2343,
      "high": 2.24,
      "low": 2.2343,
      "close": 2.235,
      "volume": 3436
    },
    {
      "t": "2025-05-13 18:39:00+00:00",
      "open": 2.235,
      "high": 2.24,
      "low": 2.235,
      "close": 2.24,
      "volume": 3013
    },
    {
      "t": "2025-05-13 18:40:00+00:00",
      "open": 2.235,
      "high": 2.24,
      "low": 2.235,
      "close": 2.235,
      "volume": 8260
    },
    {
      "t": "2025-05-13 18:41:00+00:00",
      "open": 2.2301,
      "high": 2.24,
      "low": 2.2301,
      "close": 2.235,
      "volume": 31903
    },
    {
      "t": "2025-05-13 18:42:00+00:00",
      "open": 2.24,
      "high": 2.24,
      "low": 2.235,
      "close": 2.235,
      "volume": 5694
    },
    {
      "t": "2025-05-13 18:43:00+00:00",
      "open": 2.24,
      "high": 2.24,
      "low": 2.235,
      "close": 2.235,
      "volume": 5075
    },
    {
      "t": "2025-05-13 18:44:00+00:00",
      "open": 2.2399,
      "high": 2.24,
      "low": 2.235,
      "close": 2.235,
      "volume": 3456
    },
    {
      "t": "2025-05-13 18:45:00+00:00",
      "open": 2.235,
      "high": 2.235,
      "low": 2.23,
      "close": 2.23,
      "volume": 1641
    },
    {
      "t": "2025-05-13 18:46:00+00:00",
      "open": 2.235,
      "high": 2.24,
      "low": 2.235,
      "close": 2.235,
      "volume": 2406
    },
    {
      "t": "2025-05-13 18:47:00+00:00",
      "open": 2.235,
      "high": 2.24,
      "low": 2.2345,
      "close": 2.24,
      "volume": 19638
    },
    {
      "t": "2025-05-13 18:48:00+00:00",
      "open": 2.235,
      "high": 2.24,
      "low": 2.235,
      "close": 2.24,
      "volume": 3599
    },
    {
      "t": "2025-05-13 18:49:00+00:00",
      "open": 2.24,
      "high": 2.24,
      "low": 2.235,
      "close": 2.235,
      "volume": 4256
    },
    {
      "t": "2025-05-13 18:50:00+00:00",
      "open": 2.24,
      "high": 2.24,
      "low": 2.23,
      "close": 2.235,
      "volume": 3021
    },
    {
      "t": "2025-05-13 18:51:00+00:00",
      "open": 2.24,
      "high": 2.24,
      "low": 2.23,
      "close": 2.2399,
      "volume": 12417
    },
    {
      "t": "2025-05-13 18:52:00+00:00",
      "open": 2.23,
      "high": 2.24,
      "low": 2.23,
      "close": 2.235,
      "volume": 9669
    },
    {
      "t": "2025-05-13 18:53:00+00:00",
      "open": 2.23,
      "high": 2.24,
      "low": 2.23,
      "close": 2.235,
      "volume": 3543
    },
    {
      "t": "2025-05-13 18:54:00+00:00",
      "open": 2.235,
      "high": 2.24,
      "low": 2.23,
      "close": 2.235,
      "volume": 26085
    },
    {
      "t": "2025-05-13 18:55:00+00:00",
      "open": 2.235,
      "high": 2.24,
      "low": 2.23,
      "close": 2.2359,
      "volume": 1497
    },
    {
      "t": "2025-05-13 18:56:00+00:00",
      "open": 2.23,
      "high": 2.25,
      "low": 2.23,
      "close": 2.25,
      "volume": 90179
    },
    {
      "t": "2025-05-13 18:57:00+00:00",
      "open": 2.2446,
      "high": 2.25,
      "low": 2.2446,
      "close": 2.25,
      "volume": 5293
    },
    {
      "t": "2025-05-13 18:58:00+00:00",
      "open": 2.2495,
      "high": 2.25,
      "low": 2.24,
      "close": 2.24,
      "volume": 2297
    },
    {
      "t": "2025-05-13 18:59:00+00:00",
      "open": 2.245,
      "high": 2.25,
      "low": 2.245,
      "close": 2.25,
      "volume": 4943
    },
    {
      "t": "2025-05-13 19:00:00+00:00",
      "open": 2.2454,
      "high": 2.25,
      "low": 2.24,
      "close": 2.24,
      "volume": 13313
    },
    {
      "t": "2025-05-13 19:01:00+00:00",
      "open": 2.24,
      "high": 2.25,
      "low": 2.24,
      "close": 2.25,
      "volume": 16792
    },
    {
      "t": "2025-05-13 19:02:00+00:00",
      "open": 2.245,
      "high": 2.25,
      "low": 2.245,
      "close": 2.25,
      "volume": 18619
    },
    {
      "t": "2025-05-13 19:03:00+00:00",
      "open": 2.24,
      "high": 2.25,
      "low": 2.24,
      "close": 2.245,
      "volume": 7391
    },
    {
      "t": "2025-05-13 19:04:00+00:00",
      "open": 2.245,
      "high": 2.25,
      "low": 2.2403,
      "close": 2.25,
      "volume": 5561
    },
    {
      "t": "2025-05-13 19:05:00+00:00",
      "open": 2.245,
      "high": 2.25,
      "low": 2.24,
      "close": 2.245,
      "volume": 3838
    },
    {
      "t": "2025-05-13 19:06:00+00:00",
      "open": 2.245,
      "high": 2.25,
      "low": 2.245,
      "close": 2.245,
      "volume": 34046
    },
    {
      "t": "2025-05-13 19:07:00+00:00",
      "open": 2.245,
      "high": 2.25,
      "low": 2.24,
      "close": 2.24,
      "volume": 4886
    },
    {
      "t": "2025-05-13 19:08:00+00:00",
      "open": 2.245,
      "high": 2.25,
      "low": 2.24,
      "close": 2.24,
      "volume": 33528
    },
    {
      "t": "2025-05-13 19:09:00+00:00",
      "open": 2.245,
      "high": 2.25,
      "low": 2.245,
      "close": 2.245,
      "volume": 1640
    },
    {
      "t": "2025-05-13 19:10:00+00:00",
      "open": 2.2405,
      "high": 2.25,
      "low": 2.2405,
      "close": 2.25,
      "volume": 2557
    },
    {
      "t": "2025-05-13 19:11:00+00:00",
      "open": 2.25,
      "high": 2.25,
      "low": 2.245,
      "close": 2.245,
      "volume": 76277
    },
    {
      "t": "2025-05-13 19:12:00+00:00",
      "open": 2.245,
      "high": 2.25,
      "low": 2.245,
      "close": 2.2454,
      "volume": 12123
    },
    {
      "t": "2025-05-13 19:13:00+00:00",
      "open": 2.24,
      "high": 2.25,
      "low": 2.24,
      "close": 2.25,
      "volume": 10672
    },
    {
      "t": "2025-05-13 19:14:00+00:00",
      "open": 2.25,
      "high": 2.25,
      "low": 2.2414,
      "close": 2.25,
      "volume": 3994
    },
    {
      "t": "2025-05-13 19:15:00+00:00",
      "open": 2.25,
      "high": 2.25,
      "low": 2.24,
      "close": 2.2465,
      "volume": 3650
    },
    {
      "t": "2025-05-13 19:16:00+00:00",
      "open": 2.2457,
      "high": 2.25,
      "low": 2.24,
      "close": 2.245,
      "volume": 12142
    },
    {
      "t": "2025-05-13 19:17:00+00:00",
      "open": 2.245,
      "high": 2.25,
      "low": 2.24,
      "close": 2.245,
      "volume": 11128
    },
    {
      "t": "2025-05-13 19:18:00+00:00",
      "open": 2.245,
      "high": 2.25,
      "low": 2.24,
      "close": 2.2462,
      "volume": 30384
    },
    {
      "t": "2025-05-13 19:19:00+00:00",
      "open": 2.241,
      "high": 2.25,
      "low": 2.24,
      "close": 2.24,
      "volume": 6270
    },
    {
      "t": "2025-05-13 19:20:00+00:00",
      "open": 2.24,
      "high": 2.25,
      "low": 2.24,
      "close": 2.245,
      "volume": 16048
    },
    {
      "t": "2025-05-13 19:21:00+00:00",
      "open": 2.2457,
      "high": 2.25,
      "low": 2.24,
      "close": 2.25,
      "volume": 4118
    },
    {
      "t": "2025-05-13 19:22:00+00:00",
      "open": 2.24,
      "high": 2.25,
      "low": 2.24,
      "close": 2.25,
      "volume": 2242
    },
    {
      "t": "2025-05-13 19:23:00+00:00",
      "open": 2.24,
      "high": 2.25,
      "low": 2.24,
      "close": 2.25,
      "volume": 12443
    },
    {
      "t": "2025-05-13 19:24:00+00:00",
      "open": 2.25,
      "high": 2.25,
      "low": 2.24,
      "close": 2.24,
      "volume": 14006
    },
    {
      "t": "2025-05-13 19:25:00+00:00",
      "open": 2.25,
      "high": 2.25,
      "low": 2.24,
      "close": 2.245,
      "volume": 15957
    },
    {
      "t": "2025-05-13 19:26:00+00:00",
      "open": 2.245,
      "high": 2.25,
      "low": 2.245,
      "close": 2.25,
      "volume": 19129
    },
    {
      "t": "2025-05-13 19:27:00+00:00",
      "open": 2.245,
      "high": 2.25,
      "low": 2.2408,
      "close": 2.245,
      "volume": 10373
    },
    {
      "t": "2025-05-13 19:28:00+00:00",
      "open": 2.25,
      "high": 2.25,
      "low": 2.24,
      "close": 2.2457,
      "volume": 22726
    },
    {
      "t": "2025-05-13 19:29:00+00:00",
      "open": 2.25,
      "high": 2.26,
      "low": 2.245,
      "close": 2.26,
      "volume": 237321
    },
    {
      "t": "2025-05-13 19:30:00+00:00",
      "open": 2.255,
      "high": 2.26,
      "low": 2.2502,
      "close": 2.255,
      "volume": 72147
    },
    {
      "t": "2025-05-13 19:31:00+00:00",
      "open": 2.26,
      "high": 2.26,
      "low": 2.2501,
      "close": 2.2501,
      "volume": 45302
    },
    {
      "t": "2025-05-13 19:32:00+00:00",
      "open": 2.255,
      "high": 2.26,
      "low": 2.255,
      "close": 2.26,
      "volume": 17863
    },
    {
      "t": "2025-05-13 19:33:00+00:00",
      "open": 2.255,
      "high": 2.26,
      "low": 2.2501,
      "close": 2.255,
      "volume": 13657
    },
    {
      "t": "2025-05-13 19:34:00+00:00",
      "open": 2.26,
      "high": 2.26,
      "low": 2.255,
      "close": 2.255,
      "volume": 4186
    },
    {
      "t": "2025-05-13 19:35:00+00:00",
      "open": 2.2501,
      "high": 2.26,
      "low": 2.2501,
      "close": 2.255,
      "volume": 8936
    },
    {
      "t": "2025-05-13 19:36:00+00:00",
      "open": 2.26,
      "high": 2.26,
      "low": 2.2534,
      "close": 2.2534,
      "volume": 13781
    },
    {
      "t": "2025-05-13 19:37:00+00:00",
      "open": 2.26,
      "high": 2.27,
      "low": 2.2543,
      "close": 2.265,
      "volume": 230561
    },
    {
      "t": "2025-05-13 19:38:00+00:00",
      "open": 2.27,
      "high": 2.28,
      "low": 2.265,
      "close": 2.275,
      "volume": 96459
    },
    {
      "t": "2025-05-13 19:39:00+00:00",
      "open": 2.275,
      "high": 2.28,
      "low": 2.27,
      "close": 2.2751,
      "volume": 35029
    },
    {
      "t": "2025-05-13 19:40:00+00:00",
      "open": 2.275,
      "high": 2.28,
      "low": 2.26,
      "close": 2.26,
      "volume": 206580
    },
    {
      "t": "2025-05-13 19:41:00+00:00",
      "open": 2.26,
      "high": 2.27,
      "low": 2.26,
      "close": 2.26,
      "volume": 4538
    },
    {
      "t": "2025-05-13 19:42:00+00:00",
      "open": 2.265,
      "high": 2.265,
      "low": 2.255,
      "close": 2.255,
      "volume": 106826
    },
    {
      "t": "2025-05-13 19:43:00+00:00",
      "open": 2.2565,
      "high": 2.26,
      "low": 2.2508,
      "close": 2.255,
      "volume": 210574
    },
    {
      "t": "2025-05-13 19:44:00+00:00",
      "open": 2.2598,
      "high": 2.27,
      "low": 2.2539,
      "close": 2.265,
      "volume": 88130
    },
    {
      "t": "2025-05-13 19:45:00+00:00",
      "open": 2.265,
      "high": 2.265,
      "low": 2.265,
      "close": 2.265,
      "volume": 114
    },
    {
      "t": "2025-05-13 19:46:00+00:00",
      "open": 2.265,
      "high": 2.2697,
      "low": 2.26,
      "close": 2.26,
      "volume": 14518
    },
    {
      "t": "2025-05-13 19:47:00+00:00",
      "open": 2.265,
      "high": 2.27,
      "low": 2.26,
      "close": 2.265,
      "volume": 10857
    },
    {
      "t": "2025-05-13 19:48:00+00:00",
      "open": 2.265,
      "high": 2.27,
      "low": 2.26,
      "close": 2.265,
      "volume": 4510
    },
    {
      "t": "2025-05-13 19:49:00+00:00",
      "open": 2.265,
      "high": 2.2698,
      "low": 2.26,
      "close": 2.26,
      "volume": 24938
    },
    {
      "t": "2025-05-13 19:50:00+00:00",
      "open": 2.27,
      "high": 2.27,
      "low": 2.25,
      "close": 2.255,
      "volume": 244942
    },
    {
      "t": "2025-05-13 19:51:00+00:00",
      "open": 2.25,
      "high": 2.2586,
      "low": 2.25,
      "close": 2.25,
      "volume": 14537
    },
    {
      "t": "2025-05-13 19:52:00+00:00",
      "open": 2.2501,
      "high": 2.2599,
      "low": 2.24,
      "close": 2.2499,
      "volume": 112724
    },
    {
      "t": "2025-05-13 19:53:00+00:00",
      "open": 2.245,
      "high": 2.25,
      "low": 2.24,
      "close": 2.25,
      "volume": 9757
    },
    {
      "t": "2025-05-13 19:54:00+00:00",
      "open": 2.245,
      "high": 2.25,
      "low": 2.24,
      "close": 2.245,
      "volume": 43925
    },
    {
      "t": "2025-05-13 19:55:00+00:00",
      "open": 2.245,
      "high": 2.25,
      "low": 2.24,
      "close": 2.245,
      "volume": 55168
    },
    {
      "t": "2025-05-13 19:56:00+00:00",
      "open": 2.245,
      "high": 2.25,
      "low": 2.245,
      "close": 2.245,
      "volume": 29272
    },
    {
      "t": "2025-05-13 19:57:00+00:00",
      "open": 2.245,
      "high": 2.25,
      "low": 2.2444,
      "close": 2.245,
      "volume": 43712
    },
    {
      "t": "2025-05-13 19:58:00+00:00",
      "open": 2.245,
      "high": 2.25,
      "low": 2.24,
      "close": 2.25,
      "volume": 63960
    },
    {
      "t": "2025-05-13 19:59:00+00:00",
      "open": 2.245,
      "high": 2.25,
      "low": 2.24,
      "close": 2.25,
      "volume": 91717
    }
  ]
}